srcs2md/__init__.py
srcs2md/cli.py
srcs2md/config.py
srcs2md/generator.py
srcs2md-0.1.0.dist-info/METADATA
srcs2md-0.1.0.dist-info/WHEEL
srcs2md-0.1.0.dist-info/entry_points.txt
srcs2md-0.1.0.dist-info/RECORD
